Metadata-Version: 2.3
Name: ethnicolr2
Version: 0.3.1
Summary: Predict Race/Ethnicity Based on Sequence of Characters in the Name
Keywords: race,ethnicity,names,demographics,machine-learning,census,pytorch,lstm
Author: Rajshekar, Suriyan, Gaurav Sood
Author-email: Rajshekar <rajshekar.ch@gmail.com>, Suriyan <suriyant@gmail.com>, Gaurav Sood <gsood07@gmail.com>
License: MIT
Classifier: Development Status :: 4 - Beta
Classifier: Intended Audience :: Science/Research
Classifier: Intended Audience :: Developers
Classifier: License :: OSI Approved :: MIT License
Classifier: Programming Language :: Python :: 3
Classifier: Programming Language :: Python :: 3.11
Classifier: Programming Language :: Python :: 3.12
Classifier: Programming Language :: Python :: 3.13
Classifier: Topic :: Scientific/Engineering :: Information Analysis
Classifier: Topic :: Scientific/Engineering :: Artificial Intelligence
Classifier: Topic :: Software Development :: Libraries :: Python Modules
Classifier: Topic :: Text Processing :: Linguistic
Classifier: Operating System :: OS Independent
Requires-Dist: click>=8.0.0
Requires-Dist: pandas>=1.3.0
Requires-Dist: torch==2.8.0
Requires-Dist: joblib==1.3.1
Requires-Dist: tqdm==4.66.3
Requires-Dist: scikit-learn==1.5.1
Requires-Python: >=3.11, <3.14
Project-URL: Bug Tracker, https://github.com/appeler/ethnicolr2/issues
Project-URL: Changelog, https://github.com/appeler/ethnicolr2/blob/main/CHANGELOG.md
Project-URL: Documentation, https://appeler.github.io/ethnicolr2/
Project-URL: Homepage, https://appeler.github.io/ethnicolr2/
Project-URL: Repository, https://github.com/appeler/ethnicolr2
